CHANGES.rst
README.rst
development.ini
setup.cfg
setup.py
kotti_theme_slate/__init__.py
kotti_theme_slate.egg-info/PKG-INFO
kotti_theme_slate.egg-info/SOURCES.txt
kotti_theme_slate.egg-info/dependency_links.txt
kotti_theme_slate.egg-info/entry_points.txt
kotti_theme_slate.egg-info/not-zip-safe
kotti_theme_slate.egg-info/requires.txt
kotti_theme_slate.egg-info/top_level.txt
kotti_theme_slate/static/css/README
kotti_theme_slate/static/css/bootstrap.css
kotti_theme_slate/static/css/bootstrap.min.css
kotti_theme_slate/static/img/README
kotti_theme_slate/static/img/glyphicons-halflings-white.png
kotti_theme_slate/static/img/glyphicons-halflings.png
kotti_theme_slate/static/js/README